svg/charts/__init__.py
svg/charts/bar.css
svg/charts/bar.py
svg/charts/css.py
svg/charts/graph.css
svg/charts/graph.py
svg/charts/line.py
svg/charts/pie.css
svg/charts/pie.py
svg/charts/plot.css
svg/charts/plot.py
svg/charts/schedule.py
svg/charts/time_series.py
svg/charts/util.py
svg.charts-7.3.1.dist-info/LICENSE
svg.charts-7.3.1.dist-info/METADATA
svg.charts-7.3.1.dist-info/WHEEL
svg.charts-7.3.1.dist-info/top_level.txt
svg.charts-7.3.1.dist-info/RECORD
